pzfx/__init__.py
pzfx/read.py
pzfx/write.py
pzfx-0.3.1.dist-info/METADATA
pzfx-0.3.1.dist-info/WHEEL
pzfx-0.3.1.dist-info/licenses/LICENSE
pzfx-0.3.1.dist-info/RECORD
