Metadata-Version: 2.4
Name: pzfx
Version: 0.3.1
Summary: Read and write GraphPad Prism .pzfx files
Project-URL: Homepage, https://github.com/Yue-Jiang/pypzfx
Project-URL: Repository, https://github.com/Yue-Jiang/pypzfx
Project-URL: Documentation, https://yue-jiang.github.io/pypzfx/
Author-email: Yue Jiang <rivehill@gmail.com>
License: MIT License
License-File: LICENSE
Keywords: biology,data,graphpad,prism,pzfx,scientific,statistics
Classifier: Development Status :: 4 - Beta
Classifier: Intended Audience :: Science/Research
Classifier: License :: OSI Approved :: MIT License
Classifier: Operating System :: OS Independent
Classifier: Programming Language :: Python :: 3
Classifier: Programming Language :: Python :: 3.9
Classifier: Programming Language :: Python :: 3.10
Classifier: Programming Language :: Python :: 3.11
Classifier: Programming Language :: Python :: 3.12
Classifier: Programming Language :: Python :: 3.13
Classifier: Topic :: Scientific/Engineering
Classifier: Topic :: Scientific/Engineering :: Bio-Informatics
Requires-Python: >=3.9
Requires-Dist: lxml>=4.0.0
Requires-Dist: pandas>=1.0.0
Provides-Extra: dev
Requires-Dist: pytest-cov>=4.0.0; extra == 'dev'
Requires-Dist: pytest>=7.0.0; extra == 'dev'
Provides-Extra: docs
Requires-Dist: mkdocs-jupyter>=0.24.0; extra == 'docs'
Requires-Dist: mkdocs-material>=9.0.0; extra == 'docs'
Requires-Dist: mkdocs>=1.5.0; extra == 'docs'
Requires-Dist: mkdocstrings[python]>=0.24.0; extra == 'docs'
